{
  "sections": {
    "main": {
      "type": "product",
      "settings": {}
    },
    "reviews": {
      "type": "product-reviews",
      "settings": {
        "heading": "تقييمات البنات",
        "subheading": "شاركي تجربتج وساعدي بنات ثانيين يختارون بثقة.",
        "install_hint": "ثبّتي تطبيق Judge.me من متجر تطبيقات Shopify، ثم أضيفي ويدجت التقييمات هنا من محرر الثيم."
      },
      "blocks": {}
    },
    "recommendations": {
      "type": "product-recommendations",
      "settings": {}
    },
    "recently": {
      "type": "recently-viewed",
      "settings": {
        "heading": "شفتيها مؤخّرًا"
      }
    }
  },
  "order": ["main", "reviews", "recommendations", "recently"]
}
